definite/__init__.py
definite/constants.py
definite/exceptions.py
definite/fsm.py
definite-1.0.0.dist-info/LICENSE
definite-1.0.0.dist-info/WHEEL
definite-1.0.0.dist-info/METADATA
definite-1.0.0.dist-info/RECORD
