Metadata-Version: 2.1
Name: definite
Version: 1.0.0
Summary: Simple finite state machines.
Home-page: https://github.com/toastdriven/definite
License: BSD-3-Clause
Author: Daniel Lindsley
Author-email: daniel@toastdriven.com
Requires-Python: >=3.6,<4.0
Classifier: License :: OSI Approved :: BSD License
Classifier: Programming Language :: Python :: 3
Classifier: Programming Language :: Python :: 3.10
Classifier: Programming Language :: Python :: 3.6
Classifier: Programming Language :: Python :: 3.7
Classifier: Programming Language :: Python :: 3.8
Classifier: Programming Language :: Python :: 3.9
Project-URL: Repository, https://github.com/toastdriven/definite
